<?xml version="1.0" encoding="utf-8"?>

<Patch>

    <Operation Class="PatchOperationFindMod">
		<mods>
			<li>CE+ CZARsenal</li>
		</mods>
        <match Class="PatchOperationSequence">
        <operations>
            <!-- Frolov -->
            <li Class="PatchOperationReplace">
                <xpath>Defs/ThingDef[defName="CE_Gun_Krip_Frolov"]/recipeMaker/researchPrerequisite</xpath>
                    <value>
                        <researchPrerequisite Inherit="False">Snek_BoltAction</researchPrerequisite>
                    </value>
            </li>
            <!-- TP-82 (stock) -->
            <li Class="PatchOperationReplace">
                <xpath>Defs/ThingDef[defName="CE_Gun_KripTP8two"]/recipeMaker/researchPrerequisite</xpath>
                    <value>
                        <researchPrerequisite Inherit="False">Snek_BreakAction</researchPrerequisite>
                    </value>
            </li>
            <!-- OTs-20 Gnom -->
            <li Class="PatchOperationReplace">
                <xpath>Defs/ThingDef[defName="CE_Krip_Gun_OTs20Gnom"]/recipeMaker/researchPrerequisite</xpath>
                    <value>
                        <researchPrerequisite Inherit="False">Snek_DoubleAction</researchPrerequisite>
                    </value>
            </li>
            <!-- MP-80-13T Makarov (rubber makarov) -->
            <li Class="PatchOperationAdd">
                <xpath>Defs/ThingDef[defName="CE_Gun_KripMakarovD"]/recipeMaker</xpath>
                    <value>
                        <researchPrerequisites>
                            <li>Snek_Bakelite</li>
                        </researchPrerequisites>
                    </value>
            </li>
            <!-- PDT-45T Yesaul -->
            <li Class="PatchOperationReplace">
                <xpath>Defs/ThingDef[defName="CE_Gun_KripYesaul"]/recipeMaker/researchPrerequisite</xpath>
                    <value>
                        <researchPrerequisite Inherit="False">Snek_SMG</researchPrerequisite>
                    </value>
            </li>
            <!-- Saiga-410K -->
            <li Class="PatchOperationAdd">
                <xpath>Defs/ThingDef[defName="CE_Gun_KripSiga410b"]/recipeMaker</xpath>
                    <value>
                        <researchPrerequisites>
                            <li>Snek_Bakelite</li>
                            <li>Snek_Shotguns</li>
                        </researchPrerequisites>
                    </value>
            </li>
            <!-- Toz81 -->
            <li Class="PatchOperationReplace">
                <xpath>Defs/ThingDef[defName="CE_Gun_KripToz81a"]/recipeMaker/researchPrerequisite</xpath>
                    <value>
                        <researchPrerequisite Inherit="False">Snek_DoubleAction</researchPrerequisite>
                    </value>
            </li>
            <li Class="PatchOperationAdd">
                <xpath>Defs/ThingDef[defName="CE_Gun_KripToz81a"]/recipeMaker</xpath>
                    <value>
                        <researchPrerequisites>
                            <li>Snek_BreakAction</li>
                        </researchPrerequisites>
                    </value>
            </li>
            <!-- Gana Krnka -->
            <li Class="PatchOperationAdd">
                <xpath>Defs/ThingDef[defName="CE_Gun_Krip_GanaKrnka"]/recipeMaker</xpath>
                    <value>
                        <researchPrerequisites>
                            <li>Snek_HighCaliber</li>
                        </researchPrerequisites>
                    </value>
            </li>
            <!-- RG-6 -->
            <li Class="PatchOperationAdd">
                <xpath>Defs/ThingDef[defName="CE_Gun_KripRG6A"]/recipeMaker</xpath>
                    <value>
                        <researchPrerequisites>
                            <li>Snek_DoubleAction</li>
                        </researchPrerequisites>
                    </value>
            </li>
            <!-- Device DM -->
            <li Class="PatchOperationAdd">
                <xpath>Defs/ThingDef[defName="CE_Gun_KripDM"]/recipeMaker</xpath>
                    <value>
                        <researchPrerequisites>
                            <li>Snek_BoltAction</li>
                        </researchPrerequisites>
                    </value>
            </li>
            <!-- MTs255-12 -->
            <li Class="PatchOperationReplace">
                <xpath>Defs/ThingDef[defName="CE_Gun_KripMTs25512a"]/recipeMaker/researchPrerequisite</xpath>
                    <value>
                        <researchPrerequisite Inherit="False">Snek_DoubleAction</researchPrerequisite>
                    </value>
            </li>
            <li Class="PatchOperationAdd">
                <xpath>Defs/ThingDef[defName="CE_Gun_KripMTs25512a"]/recipeMaker</xpath>
                    <value>
                        <researchPrerequisites>
                            <li>Snek_Bakelite</li>
                            <li>CE_SimpleNV</li>
                        </researchPrerequisites>
                    </value>
            </li>
            <!-- MTs255-20 -->
            <li Class="PatchOperationReplace">
                <xpath>Defs/ThingDef[defName="CE_Gun_KripMTs255b"]/recipeMaker/researchPrerequisite</xpath>
                    <value>
                        <researchPrerequisite Inherit="False">Snek_DoubleAction</researchPrerequisite>
                    </value>
            </li>
            <!-- MTs255-20 sawed -->
            <li Class="PatchOperationReplace">
                <xpath>Defs/ThingDef[defName="CE_Gun_KripMTs255Sawed"]/recipeMaker/researchPrerequisite</xpath>
                    <value>
                        <researchPrerequisite Inherit="False">Snek_DoubleAction</researchPrerequisite>
                    </value>
            </li>
            <!-- MTs 20-01 -->
            <li Class="PatchOperationReplace">
                <xpath>Defs/ThingDef[defName="CE_Gun_Krip_MTs20a"]/recipeMaker/researchPrerequisite</xpath>
                    <value>
                        <researchPrerequisite Inherit="False">Snek_BoltAction</researchPrerequisite>
                    </value>
            </li>
            <!-- TOZ 106 -->
            <li Class="PatchOperationReplace">
                <xpath>Defs/ThingDef[defName="CE_Gun_Krip_TOZ106a"]/recipeMaker/researchPrerequisite</xpath>
                    <value>
                        <researchPrerequisite Inherit="False">Snek_BoltAction</researchPrerequisite>
                    </value>
            </li>
            <!-- IZh-43 -->
            <li Class="PatchOperationReplace">
                <xpath>Defs/ThingDef[defName="CE_Gun_Krip_IZh43a"]/recipeMaker/researchPrerequisite</xpath>
                    <value>
                        <researchPrerequisite Inherit="False">Snek_BreakAction</researchPrerequisite>
                    </value>
            </li>
            <!-- IZh-43 45-70 -->
            <li Class="PatchOperationReplace">
                <xpath>Defs/ThingDef[defName="CE_Gun_Krip_IZh43b"]/recipeMaker/researchPrerequisite</xpath>
                    <value>
                        <researchPrerequisite Inherit="False">Snek_BreakAction</researchPrerequisite>
                    </value>
            </li>
            <!-- KS-23 -->
            <li Class="PatchOperationReplace">
                <xpath>Defs/ThingDef[defName="CE_Gun_Krip_KS23a"]/recipeMaker/researchPrerequisite</xpath>
                    <value>
                        <researchPrerequisite Inherit="False">Snek_PumpAction</researchPrerequisite>
                    </value>
            </li>
            <li Class="PatchOperationAdd">
                <xpath>Defs/ThingDef[defName="CE_Gun_Krip_KS23a"]/recipeMaker</xpath>
                    <value>
                        <researchPrerequisites>
                            <li>Snek_Bakelite</li>
                            <li>Snek_HighCaliber</li>
                        </researchPrerequisites>
                    </value>
            </li>
            <!-- KS-23 Drozd -->
            <li Class="PatchOperationReplace">
                <xpath>Defs/ThingDef[defName="CE_Gun_Krip_KS23b"]/recipeMaker/researchPrerequisite</xpath>
                    <value>
                        <researchPrerequisite Inherit="False">Snek_PumpAction</researchPrerequisite>
                    </value>
            </li>
            <li Class="PatchOperationAdd">
                <xpath>Defs/ThingDef[defName="CE_Gun_Krip_KS23b"]/recipeMaker</xpath>
                    <value>
                        <researchPrerequisites>
                            <li>Snek_Bakelite</li>
                            <li>Snek_HighCaliber</li>
                        </researchPrerequisites>
                    </value>
            </li>
            <!-- Bars-1 -->
            <li Class="PatchOperationReplace">
                <xpath>Defs/ThingDef[defName="CE_Gun_Krip_Bars"]/recipeMaker/researchPrerequisite</xpath>
                    <value>
                        <researchPrerequisite Inherit="False">Snek_BoltAction</researchPrerequisite>
                    </value>
            </li>
            <!-- pl14 (i think its a wood grip)
            <li Class="PatchOperationAdd">
                <xpath>Defs/ThingDef[defName="CE_Gun_KripPL14a"]/recipeMaker</xpath>
                    <value>
                        <researchPrerequisites>
                            <li>Snek_Bakelite</li>
                        </researchPrerequisites>
                    </value> 
            </li>-->
            <!-- PLK -->
            <li Class="PatchOperationAdd">
                <xpath>Defs/ThingDef[defName="CE_Gun_KripPLK"]/recipeMaker</xpath>
                    <value>
                        <researchPrerequisites>
                            <li>Snek_Bakelite</li>
                        </researchPrerequisites>
                    </value>
            </li>
            <!-- PL-15 -->
            <li Class="PatchOperationAdd">
                <xpath>Defs/ThingDef[defName="CE_Gun_KripPL15a"]/recipeMaker</xpath>
                    <value>
                        <researchPrerequisites>
                            <li>Snek_Bakelite</li>
                        </researchPrerequisites>
                    </value>
            </li>
            <!-- PP 2000 -->
            <li Class="PatchOperationReplace">
                <xpath>Defs/ThingDef[defName="CE_Gun_KripPP2000a"]/recipeMaker/researchPrerequisite</xpath>
                    <value>
                        <researchPrerequisite Inherit="False">Snek_SMG</researchPrerequisite>
                    </value>
            </li>
            <li Class="PatchOperationAdd">
                <xpath>Defs/ThingDef[defName="CE_Gun_KripPP2000a"]/recipeMaker</xpath>
                    <value>
                        <researchPrerequisites>
                            <li>Snek_Bakelite</li>
                            <li>CE_SimpleNV</li>
                        </researchPrerequisites>
                    </value>
            </li>
            <!-- PP 2000 extended -->
            <li Class="PatchOperationReplace">
                <xpath>Defs/ThingDef[defName="CE_Gun_KripPP2000b"]/recipeMaker/researchPrerequisite</xpath>
                    <value>
                        <researchPrerequisite Inherit="False">Snek_SMG</researchPrerequisite>
                    </value>
            </li>
            <li Class="PatchOperationAdd">
                <xpath>Defs/ThingDef[defName="CE_Gun_KripPP2000b"]/recipeMaker</xpath>
                    <value>
                        <researchPrerequisites>
                            <li>Snek_Bakelite</li>
                            <li>CE_SimpleNV</li>
                        </researchPrerequisites>
                    </value>
            </li>
            <!-- PPT-27 -->
            <li Class="PatchOperationReplace">
                <xpath>Defs/ThingDef[defName="CE_Gun_PPT-27a"]/recipeMaker/researchPrerequisite</xpath>
                    <value>
                        <researchPrerequisite Inherit="False">Snek_SMG</researchPrerequisite>
                    </value>
            </li>
            <!-- Nagant Revolver -->
            <li Class="PatchOperationReplace">
                <xpath>Defs/ThingDef[defName="CE_Gun_NagantM1895a"]/recipeMaker/researchPrerequisite</xpath>
                    <value>
                        <researchPrerequisite Inherit="False">Snek_DoubleAction</researchPrerequisite>
                    </value>
            </li>
            <!-- Nagant Revolver Bramit -->
            <li Class="PatchOperationReplace">
                <xpath>Defs/ThingDef[defName="CE_Gun_NagantM1895b"]/recipeMaker/researchPrerequisite</xpath>
                    <value>
                        <researchPrerequisite Inherit="False">Snek_DoubleAction</researchPrerequisite>
                    </value>
            </li>
            <!-- Makarov -->
            <li Class="PatchOperationAdd">
                <xpath>Defs/ThingDef[defName="CE_Gun_KripMakarovB"]/recipeMaker</xpath>
                    <value>
                        <researchPrerequisites>
                            <li>Snek_Bakelite</li>
                        </researchPrerequisites>
                    </value>
            </li>
            <!-- Makarov Drum -->
            <li Class="PatchOperationAdd">
                <xpath>Defs/ThingDef[defName="CE_Gun_KripMakarovC"]/recipeMaker</xpath>
                    <value>
                        <researchPrerequisites>
                            <li>Snek_Bakelite</li>
                        </researchPrerequisites>
                    </value>
            </li>
            <!-- Makarov PMM -->
            <li Class="PatchOperationAdd">
                <xpath>Defs/ThingDef[defName="CE_Gun_KripPMM"]/recipeMaker</xpath>
                    <value>
                        <researchPrerequisites>
                            <li>Snek_Bakelite</li>
                        </researchPrerequisites>
                    </value>
            </li>
            <!-- APS "Stechkin" -->
            <li Class="PatchOperationReplace">
                <xpath>Defs/ThingDef[defName="CE_Gun_KripAPS"]/recipeMaker/researchPrerequisite</xpath>
                    <value>
                        <researchPrerequisite Inherit="False">Snek_SMG</researchPrerequisite>
                    </value>
            </li>
            <!-- KEDR -->
            <li Class="PatchOperationReplace">
                <xpath>Defs/ThingDef[defName="CE_Gun_KripKEDR"]/recipeMaker/researchPrerequisite</xpath>
                    <value>
                        <researchPrerequisite Inherit="False">Snek_SMG</researchPrerequisite>
                    </value>
            </li>
            <!-- PP-19 Bizon 2 -->
            <li Class="PatchOperationReplace">
                <xpath>Defs/ThingDef[defName="CE_Gun_KripPP19a"]/recipeMaker/researchPrerequisite</xpath>
                    <value>
                        <researchPrerequisite Inherit="False">Snek_SMG</researchPrerequisite>
                    </value>
            </li>
            <li Class="PatchOperationAdd">
                <xpath>Defs/ThingDef[defName="CE_Gun_KripPP19a"]/recipeMaker</xpath>
                    <value>
                        <researchPrerequisites>
                            <li>Snek_Bakelite</li>
                        </researchPrerequisites>
                    </value>
            </li>
            <!-- PPS-43M -->
            <li Class="PatchOperationReplace">
                <xpath>Defs/ThingDef[defName="CE_Gun_PPS43M"]/recipeMaker/researchPrerequisite</xpath>
                    <value>
                        <researchPrerequisite Inherit="False">Snek_SMG</researchPrerequisite>
                    </value>
            </li>
            <!-- PPSH-41 -->
            <li Class="PatchOperationReplace">
                <xpath>Defs/ThingDef[defName="CE_Gun_PPSH"]/recipeMaker/researchPrerequisite</xpath>
                    <value>
                        <researchPrerequisite Inherit="False">Snek_SMG</researchPrerequisite>
                    </value>
            </li>
            <!-- AO-64 -->
            <li Class="PatchOperationReplace">
                <xpath>Defs/ThingDef[defName="CE_Gun_KripAO64a"]/recipeMaker/researchPrerequisite</xpath>
                    <value>
                        <researchPrerequisite Inherit="False">GasOperation</researchPrerequisite>
                    </value>
            </li>
            <li Class="PatchOperationAdd">
                <xpath>Defs/ThingDef[defName="CE_Gun_KripAO64a"]/recipeMaker</xpath>
                    <value>
                        <researchPrerequisites>
                            <li>Snek_AmmoBelts</li>
                            <li>Snek_SimpleScopes</li>
                        </researchPrerequisites>
                    </value>
            </li>
            <!-- Grad -->
            <li Class="PatchOperationAdd">
                <xpath>Defs/ThingDef[defName="CE_Gun_KripGrad"]/recipeMaker</xpath>
                    <value>
                        <researchPrerequisites>
                            <li>Snek_Bakelite</li>
                            <li>Snek_ModernScopes</li>
                        </researchPrerequisites>
                    </value>
            </li>
            <!-- Medved -->
            <li Class="PatchOperationAdd">
                <xpath>Defs/ThingDef[defName="CE_Gun_Medved"]/recipeMaker</xpath>
                    <value>
                        <researchPrerequisites>
                            <li>Snek_SimpleScopes</li>
                        </researchPrerequisites>
                    </value>
            </li>
            <!-- Toz-55 -->
            <li Class="PatchOperationReplace">
                <xpath>Defs/ThingDef[defName="CE_Gun_TOZ55a"]/recipeMaker/researchPrerequisite</xpath>
                    <value>
                        <researchPrerequisite Inherit="False">Snek_BreakAction</researchPrerequisite>
                    </value>
            </li>
            <li Class="PatchOperationAdd">
                <xpath>Defs/ThingDef[defName="CE_Gun_TOZ55a"]/recipeMaker</xpath>
                    <value>
                        <researchPrerequisites>
                            <li>Snek_SimpleScopes</li>
                        </researchPrerequisites>
                    </value>
            </li>
            <!-- Toz-55 shorty -->
            <li Class="PatchOperationReplace">
                <xpath>Defs/ThingDef[defName="CE_Gun_TOZ55Sawed"]/recipeMaker/researchPrerequisite</xpath>
                    <value>
                        <researchPrerequisite Inherit="False">Snek_BreakAction</researchPrerequisite>
                    </value>
            </li>
            <!-- IZh-94 Express -->
            <li Class="PatchOperationReplace">
                <xpath>Defs/ThingDef[defName="CE_Gun_KripIZh-94b"]/recipeMaker/researchPrerequisite</xpath>
                    <value>
                        <researchPrerequisite Inherit="False">Snek_BreakAction</researchPrerequisite>
                    </value>
            </li>
            <!-- IZh-94 Taiga -->
            <li Class="PatchOperationReplace">
                <xpath>Defs/ThingDef[defName="CE_Gun_KripIZh-94a"]/recipeMaker/researchPrerequisite</xpath>
                    <value>
                        <researchPrerequisite Inherit="False">Snek_BreakAction</researchPrerequisite>
                    </value>
            </li>
            <!-- monte carlo -->
            <li Class="PatchOperationAdd">
                <xpath>Defs/ThingDef[defName="CE_Gun_Krip_MonteCarlo"]/recipeMaker</xpath>
                    <value>
                        <researchPrerequisites>
                            <li>Snek_ModernScopes</li>
                            <li>Snek_Bakelite</li>
                        </researchPrerequisites>
                    </value>
            </li>
            <!-- Fedorov Avtomat -->
            <li Class="PatchOperationReplace">
                <xpath>Defs/ThingDef[defName="CE_Gun_Krip_Fedorov"]/recipeMaker/researchPrerequisite</xpath>
                    <value>
                        <researchPrerequisite Inherit="False">Snek_SelfLoad</researchPrerequisite>
                    </value>
            </li>
            <!-- Arisaka Type 30 -->
            <li Class="PatchOperationReplace">
                <xpath>Defs/ThingDef[defName="CE_Gun_Krip_Arisaka30a"]/recipeMaker/researchPrerequisite</xpath>
                    <value>
                        <researchPrerequisite Inherit="False">Snek_BoltAction</researchPrerequisite>
                    </value>
            </li>
            <!-- AO-46 -->
            <li Class="PatchOperationReplace">
                <xpath>Defs/ThingDef[defName="CE_Gun_Krip_AO46a"]/recipeMaker/researchPrerequisite</xpath>
                    <value>
                        <researchPrerequisite Inherit="False">Snek_SelectiveFire</researchPrerequisite>
                    </value>
            </li>
            <!-- AK-104 -->
            <li Class="PatchOperationAdd">
                <xpath>Defs/ThingDef[defName="CE_Gun_Krip_AK104a"]/recipeMaker</xpath>
                    <value>
                        <researchPrerequisites>
                            <li>Snek_Bakelite</li>
                        </researchPrerequisites>
                    </value>
            </li>
            <!-- AK-104 Tactical -->
            <li Class="PatchOperationAdd">
                <xpath>Defs/ThingDef[defName="CE_Gun_Krip_AK104b"]/recipeMaker</xpath>
                    <value>
                        <researchPrerequisites>
                            <li>Snek_ModernScopes</li>
                            <li>Snek_Bakelite</li>
                        </researchPrerequisites>
                    </value>
            </li>
            <!-- AK-105 -->
            <li Class="PatchOperationAdd">
                <xpath>Defs/ThingDef[defName="CE_Gun_Krip_AK105a"]/recipeMaker</xpath>
                    <value>
                        <researchPrerequisites>
                            <li>Snek_Bakelite</li>
                        </researchPrerequisites>
                    </value>
            </li>
            <!-- SVT-40 PU -->
            <li Class="PatchOperationAdd">
                <xpath>Defs/ThingDef[defName="CE_Gun_Krip_SVTPU"]/recipeMaker</xpath>
                    <value>
                        <researchPrerequisites>
                            <li>Snek_SimpleScopes</li>
                        </researchPrerequisites>
                    </value>
            </li>
            <!-- AVS 36 -->
            <li Class="PatchOperationReplace">
                <xpath>Defs/ThingDef[defName="CE_Gun_Krip_AVS"]/recipeMaker/researchPrerequisite</xpath>
                    <value>
                        <researchPrerequisite Inherit="False">Snek_SelectiveFire</researchPrerequisite>
                    </value>
            </li>
            <!-- SVU-A Dragunov -->
            <li Class="PatchOperationAdd">
                <xpath>Defs/ThingDef[defName="CE_Gun_Krip_SVU"]/recipeMaker</xpath>
                    <value>
                        <researchPrerequisites>
                            <li>Snek_ModernScopes</li>
                            <li>Snek_Bakelite</li>
                        </researchPrerequisites>
                    </value>
            </li>
            <!-- SV98 -->
            <li Class="PatchOperationReplace">
                <xpath>Defs/ThingDef[defName="CE_Gun_Krip_SV98a"]/recipeMaker/researchPrerequisite</xpath>
                    <value>
                        <researchPrerequisite Inherit="False">Snek_BoltAction</researchPrerequisite>
                    </value>
            </li>
            <li Class="PatchOperationAdd">
                <xpath>Defs/ThingDef[defName="CE_Gun_Krip_SV98a"]/recipeMaker</xpath>
                    <value>
                        <researchPrerequisites>
                            <li>Snek_SimpleScopes</li>
                        </researchPrerequisites>
                    </value>
            </li>
            <!-- SV98M -->
            <li Class="PatchOperationReplace">
                <xpath>Defs/ThingDef[defName="CE_Gun_Krip_SV98b"]/recipeMaker/researchPrerequisites</xpath>
                    <value>
                        <researchPrerequisites>
                            <li>PrecisionRifling</li>
                            <li>Snek_ModernScopes</li>
                            <li>Snek_Bakelite</li>
                            <li>CE_AdvancedNV</li>
                        </researchPrerequisites>
                    </value>
            </li>
            <!-- SVD -->
            <li Class="PatchOperationAdd">
                <xpath>Defs/ThingDef[defName="CE_Gun_Krip_SVD"]/recipeMaker</xpath>
                    <value>
                        <researchPrerequisites>
                            <li>Snek_SimpleScopes</li>
                        </researchPrerequisites>
                    </value>
            </li>
            <!-- 9A-91 -->
            <li Class="PatchOperationAdd">
                <xpath>Defs/ThingDef[defName="CE_Gun_Krip9A91aCompact"]/recipeMaker</xpath>
                    <value>
                        <researchPrerequisites>
                            <li>Snek_Bakelite</li>
                        </researchPrerequisites>
                    </value>
            </li>
            <!-- 9A-91 -->
            <li Class="PatchOperationAdd">
                <xpath>Defs/ThingDef[defName="CE_Gun_Krip9A91a"]/recipeMaker</xpath>
                    <value>
                        <researchPrerequisites>
                            <li>Snek_Bakelite</li>
                            <li>CE_SimpleNV</li>
                        </researchPrerequisites>
                    </value>
            </li>
            <!-- AK-74 -->
            <li Class="PatchOperationReplace">
                <xpath>Defs/ThingDef[defName="CE_Gun_KripAK74a"]/recipeMaker/researchPrerequisite</xpath>
                    <value>
                        <researchPrerequisite Inherit="False">Snek_SelectiveFire</researchPrerequisite>
                    </value>
            </li>
            <li Class="PatchOperationAdd">
                <xpath>Defs/ThingDef[defName="CE_Gun_KripAK74a"]/recipeMaker</xpath>
                    <value>
                        <researchPrerequisites>
                            <li>Snek_Bakelite</li>
                        </researchPrerequisites>
                    </value>
            </li>
            <!-- AK-74 GP-25 -->
            <li Class="PatchOperationReplace">
                <xpath>Defs/ThingDef[defName="CE_Gun_KripAK74GL"]/recipeMaker/researchPrerequisites</xpath>
                    <value>
                        <researchPrerequisites>
                            <li>Snek_SelectiveFire</li>
                            <li>Snek_Bakelite</li>
                            <li>CE_Launchers</li>
                        </researchPrerequisites>
                    </value>
            </li>
            <!-- AKS-74 -->
            <li Class="PatchOperationReplace">
                <xpath>Defs/ThingDef[defName="CE_Gun_KripAK74b"]/recipeMaker/researchPrerequisite</xpath>
                    <value>
                        <researchPrerequisite Inherit="False">Snek_SelectiveFire</researchPrerequisite>
                    </value>
            </li>
            <li Class="PatchOperationAdd">
                <xpath>Defs/ThingDef[defName="CE_Gun_KripAK74b"]/recipeMaker</xpath>
                    <value>
                        <researchPrerequisites>
                            <li>Snek_Bakelite</li>
                        </researchPrerequisites>
                    </value>
            </li>
            <!-- AK-74M -->
            <li Class="PatchOperationAdd">
                <xpath>Defs/ThingDef[defName="CE_Gun_KripAK74d"]/recipeMaker</xpath>
                    <value>
                        <researchPrerequisites>
                            <li>Snek_Bakelite</li>
                            <li>CE_SimpleNV</li>
                        </researchPrerequisites>
                    </value>
            </li>
            <!-- RPK-74M -->
            <li Class="PatchOperationAdd">
                <xpath>Defs/ThingDef[defName="CE_Gun_KripRPK74M"]/recipeMaker</xpath>
                    <value>
                        <researchPrerequisites>
                            <li>Snek_Bakelite</li>
                        </researchPrerequisites>
                    </value>
            </li>
            <!-- AK-74M -->
            <li Class="PatchOperationAdd">
                <xpath>Defs/ThingDef[defName="CE_Gun_KripAK74d"]/recipeMaker</xpath>
                    <value>
                        <researchPrerequisites>
                            <li>Snek_Bakelite</li>
                            <li>CE_SimpleNV</li>
                        </researchPrerequisites>
                    </value>
            </li>
            <!-- AKS-74u-->
            <li Class="PatchOperationReplace">
                <xpath>Defs/ThingDef[defName="CE_Gun_KripAK74u"]/recipeMaker/researchPrerequisite</xpath>
                    <value>
                        <researchPrerequisite Inherit="False">Snek_SelectiveFire</researchPrerequisite>
                    </value>
            </li>
            <li Class="PatchOperationAdd">
                <xpath>Defs/ThingDef[defName="CE_Gun_KripAK74u"]/recipeMaker</xpath>
                    <value>
                        <researchPrerequisites>
                            <li>Snek_Bakelite</li>
                        </researchPrerequisites>
                    </value>
            </li>
            <!-- AK-74M Zenitco-->
            <li Class="PatchOperationReplace">
                <xpath>Defs/ThingDef[defName="CE_Gun_KripAK74c"]/recipeMaker/researchPrerequisite</xpath>
                    <value>
                        <researchPrerequisite Inherit="False">Snek_SelectiveFire</researchPrerequisite>
                    </value>
            </li>
            <li Class="PatchOperationAdd">
                <xpath>Defs/ThingDef[defName="CE_Gun_KripAK74c"]/recipeMaker</xpath>
                    <value>
                        <researchPrerequisites>
                            <li>Snek_Bakelite</li>
                            <li>CE_SimpleNV</li>
                        </researchPrerequisites>
                    </value>
            </li>
            <!-- AKS-74u Zenitco -->
            <li Class="PatchOperationAdd">
                <xpath>Defs/ThingDef[defName="CE_Gun_KripAK74uZen"]/recipeMaker</xpath>
                    <value>
                        <researchPrerequisites>
                            <li>Snek_Bakelite</li>
                            <li>CE_SimpleNV</li>
                        </researchPrerequisites>
                    </value>
            </li>
            <!-- AKM-->
            <li Class="PatchOperationReplace">
                <xpath>Defs/ThingDef[defName="CE_Gun_AKM"]/recipeMaker/researchPrerequisite</xpath>
                    <value>
                        <researchPrerequisite Inherit="False">Snek_SelectiveFire</researchPrerequisite>
                    </value>
            </li>
            <!-- RPKS-->
            <li Class="PatchOperationReplace">
                <xpath>Defs/ThingDef[defName="CE_Gun_RPKS"]/recipeMaker/researchPrerequisite</xpath>
                    <value>
                        <researchPrerequisite Inherit="False">Snek_SelectiveFire</researchPrerequisite>
                    </value>
            </li>
            <li Class="PatchOperationAdd">
                <xpath>Defs/ThingDef[defName="CE_Gun_RPKS"]/recipeMaker</xpath>
                    <value>
                        <researchPrerequisites>
                            <li>Snek_LMG</li>
                        </researchPrerequisites>
                    </value>
            </li>
            <!-- AKML "NSP-3"-->
            <li Class="PatchOperationReplace">
                <xpath>Defs/ThingDef[defName="CE_Gun_KripAKMNV"]/recipeMaker/researchPrerequisites</xpath>
                    <value>
                        <researchPrerequisites>
                            <li>Snek_SelectiveFire</li>
                            <li>CE_SimpleNV</li>
                        </researchPrerequisites>
                    </value>
            </li>
            <!-- AKMP -->
            <li Class="PatchOperationAdd">
                <xpath>Defs/ThingDef[defName="CE_Gun_KripAKMP"]/recipeMaker</xpath>
                    <value>
                        <researchPrerequisites>
                            <li>Snek_Bakelite</li>
                        </researchPrerequisites>
                    </value>
            </li>
            <!-- AKMS "Tishina" -->
            <li Class="PatchOperationReplace">
                <xpath>Defs/ThingDef[defName="CE_Gun_KripAKMSGL"]/recipeMaker/researchPrerequisites</xpath>
                    <value>
                        <researchPrerequisites>
                            <li>Snek_SelectiveFire</li>
                            <li>CE_Launchers</li>
                        </researchPrerequisites>
                    </value>
            </li>
            <!-- AN-94 -->
            <li Class="PatchOperationAdd">
                <xpath>Defs/ThingDef[defName="CE_Gun_KripAn94A"]/recipeMaker</xpath>
                    <value>
                        <researchPrerequisites>
                            <li>Snek_Bakelite</li>
                        </researchPrerequisites>
                    </value>
            </li>
            <!-- AN-94 Tactical -->
            <li Class="PatchOperationReplace">
                <xpath>Defs/ThingDef[defName="CE_Gun_KripAn94C"]/recipeMaker/researchPrerequisites</xpath>
                    <value>
                        <researchPrerequisites>
                            <li>PrecisionRifling</li>
                            <li>CE_Launchers</li>
                            <li>Snek_Bakelite</li>
                            <li>Snek_ModernScopes</li>
                        </researchPrerequisites>
                    </value>
            </li>
            <!-- DP-27 (lmao some dumbass made the def DP17 :Ce_kekclap:-->
            <li Class="PatchOperationAdd">
                <xpath>Defs/ThingDef[defName="CE_Gun_KripDP17a"]/recipeMaker</xpath>
                    <value>
                        <researchPrerequisites>
                            <li>Snek_LMG</li>
                        </researchPrerequisites>
                    </value>
            </li>
            <!-- DTM -->
            <li Class="PatchOperationAdd">
                <xpath>Defs/ThingDef[defName="CE_Gun_KripDTMa"]/recipeMaker</xpath>
                    <value>
                        <researchPrerequisites>
                            <li>Snek_LMG</li>
                        </researchPrerequisites>
                    </value>
            </li>
            <!-- RPD -->
            <li Class="PatchOperationAdd">
                <xpath>Defs/ThingDef[defName="CE_Gun_Krip_RPD"]/recipeMaker</xpath>
                    <value>
                        <researchPrerequisites>
                            <li>Snek_AmmoBelts</li>
                        </researchPrerequisites>
                    </value>
            </li>
            <!-- RPD tactical -->
            <li Class="PatchOperationAdd">
                <xpath>Defs/ThingDef[defName="CE_Gun_Krip_RPDT"]/recipeMaker</xpath>
                    <value>
                        <researchPrerequisites>
                            <li>Snek_AmmoBelts</li>
                            <li>Snek_Bakelite</li>
                            <li>CE_SimpleNV</li>
                        </researchPrerequisites>
                    </value>
            </li>
            <!-- MOSIN TIME WOOOOOOOOOO -->
            <!-- Mosin–Nagant M1891 -->
            <li Class="PatchOperationReplace">
                <xpath>Defs/ThingDef[defName="CE_Gun_Krip_Mosin1891a"]/recipeMaker/researchPrerequisite</xpath>
                    <value>
                        <researchPrerequisite Inherit="False">Snek_BoltAction</researchPrerequisite>
                    </value>
            </li>
            <!-- Mosin–Nagant OBREZ -->
            <li Class="PatchOperationReplace">
                <xpath>Defs/ThingDef[defName="CE_Gun_Krip_MosinObrez"]/recipeMaker/researchPrerequisite</xpath>
                    <value>
                        <researchPrerequisite Inherit="False">Snek_BoltAction</researchPrerequisite>
                    </value>
            </li>
            <!-- Mosin–Nagant M91/30 -->
            <li Class="PatchOperationReplace">
                <xpath>Defs/ThingDef[defName="CE_Gun_Krip_Mosin9130s"]/recipeMaker/researchPrerequisite</xpath>
                    <value>
                        <researchPrerequisite Inherit="False">Snek_BoltAction</researchPrerequisite>
                    </value>
            </li>
            <!-- Mosin–Nagant M91/30 PU -->
            <li Class="PatchOperationReplace">
                <xpath>Defs/ThingDef[defName="CE_Gun_Krip_MosinPU"]/recipeMaker/researchPrerequisite</xpath>
                    <value>
                        <researchPrerequisite Inherit="False">Snek_BoltAction</researchPrerequisite>
                    </value>
            </li>
            <li Class="PatchOperationAdd">
                <xpath>Defs/ThingDef[defName="CE_Gun_Krip_MosinPU"]/recipeMaker</xpath>
                    <value>
                        <researchPrerequisites>
                            <li>Snek_SimpleScopes</li>
                        </researchPrerequisites>
                    </value>
            </li>
            <!-- Mosin–Nagant M44 -->
            <li Class="PatchOperationReplace">
                <xpath>Defs/ThingDef[defName="CE_Gun_Krip_Mosin44a"]/recipeMaker/researchPrerequisite</xpath>
                    <value>
                        <researchPrerequisite Inherit="False">Snek_BoltAction</researchPrerequisite>
                    </value>
            </li>
            <!-- Archangel -->
            <li Class="PatchOperationAdd">
                <xpath>Defs/ThingDef[defName="CE_Gun_Krip_Archangel"]/recipeMaker</xpath>
                    <value>
                        <researchPrerequisites>
                            <li>Snek_ModernScopes</li>
                            <li>Snek_Bakelite</li>
                        </researchPrerequisites>
                    </value>
            </li>
            <!-- Kord -->
            <li Class="PatchOperationReplace">
                <xpath>Defs/ThingDef[defName="CE_Gun_Serina_KordPortable"]/recipeMaker/researchPrerequisites</xpath>
                    <value>
                        <researchPrerequisites>
                            <li>CE_TurretHeavyWeapons</li>
                            <li>PrecisionRifling</li>
                            <li>Snek_SimpleScopes</li>
                            <li>Snek_Bakelite</li>
                            <li>Snek_HighCaliber</li>
                            <li>Snek_AmmoBelts</li>
                        </researchPrerequisites>
                    </value>
            </li>
            <!-- ASVK-M -->
            <li Class="PatchOperationAdd">
                <xpath>Defs/ThingDef[defName="CE_Gun_Krip_ASVK-M"]/recipeMaker</xpath>
                    <value>
                        <researchPrerequisites>
                            <li>Snek_ModernScopes</li>
                            <li>Snek_Bakelite</li>
                            <li>Snek_HighCaliber</li>
                        </researchPrerequisites>
                    </value>
            </li>
            <!-- DShK -->
            <li Class="PatchOperationReplace">
                <xpath>Defs/ThingDef[defName="CE_DShK_Aug"]/researchPrerequisites</xpath>
                    <value>
                        <researchPrerequisites>
                            <li>PrecisionRifling</li>
                            <li>CE_TurretHeavyWeapons</li>
                            <li>Snek_AmmoBelts</li>
                        </researchPrerequisites>
                    </value>
            </li>
            <!-- Maxim -->
            <li Class="PatchOperationReplace">
                <xpath>Defs/ThingDef[defName="CE_Maxim_Aug"]/researchPrerequisites</xpath>
                    <value>
                        <researchPrerequisites>
                            <li>BlowbackOperation</li>
                            <li>CE_TurretHeavyWeapons</li>
                            <li>Snek_AmmoBelts</li>
                        </researchPrerequisites>
                    </value>
            </li>
            <!-- S&W M3 russian -->
            <li Class="PatchOperationReplace">
                <xpath>Defs/ThingDef[defName="CE_Gun_SWModel3Rus"]/recipeMaker/researchPrerequisite</xpath>
                    <value>
                        <researchPrerequisite Inherit="False">Snek_BreakAction</researchPrerequisite>
                    </value>
            </li>
            <!-- winchester 1895 -->
            <li Class="PatchOperationReplace">
                <xpath>Defs/ThingDef[defName="CE_Gun_Win1895a"]/recipeMaker/researchPrerequisite</xpath>
                    <value>
                        <researchPrerequisite Inherit="False">Snek_BoltAction</researchPrerequisite>
                    </value>
            </li>
            <!-- winchester 1895 saddle ring -->
            <li Class="PatchOperationReplace">
                <xpath>Defs/ThingDef[defName="CE_Gun_Win1895b"]/recipeMaker/researchPrerequisite</xpath>
                    <value>
                        <researchPrerequisite Inherit="False">Snek_BoltAction</researchPrerequisite>
                    </value>
            </li>
            <!-- MTs-558 -->
            <li Class="PatchOperationReplace">
                <xpath>Defs/ThingDef[defName="CE_Gun_MTs558a"]/recipeMaker/researchPrerequisite</xpath>
                    <value>
                        <researchPrerequisite Inherit="False">Snek_BoltAction</researchPrerequisite>
                    </value>
            </li>
            <li Class="PatchOperationAdd">
                <xpath>Defs/ThingDef[defName="CE_Gun_MTs558a"]/recipeMaker</xpath>
                    <value>
                        <researchPrerequisites>
                            <li>Snek_Bakelite</li>
                            <li>Snek_HighCaliber</li>
                        </researchPrerequisites>
                    </value>
            </li>
            <!-- RSh-12 -->
            <li Class="PatchOperationReplace">
                <xpath>Defs/ThingDef[defName="CE_Gun_Rsh-12a"]/recipeMaker/researchPrerequisite</xpath>
                    <value>
                        <researchPrerequisite Inherit="False">Snek_DoubleAction</researchPrerequisite>
                    </value>
            </li>
            <li Class="PatchOperationAdd">
                <xpath>Defs/ThingDef[defName="CE_Gun_Rsh-12a"]/recipeMaker</xpath>
                    <value>
                        <researchPrerequisites>
                            <li>Snek_Bakelite</li>
                            <li>Snek_HighCaliber</li>
                        </researchPrerequisites>
                    </value>
            </li>
            <!-- M1923 Thompson -->
            <li Class="PatchOperationReplace">
                <xpath>Defs/ThingDef[defName="Krip_CE_Gun_M1923Thompson"]/recipeMaker/researchPrerequisite</xpath>
                    <value>
                        <researchPrerequisite Inherit="False">Snek_SMG</researchPrerequisite>
                    </value>
            </li>
            <!-- Škorpion -->
            <li Class="PatchOperationReplace">
                <xpath>Defs/ThingDef[defName="CE_Gun_VZ61b"]/recipeMaker/researchPrerequisite</xpath>
                    <value>
                        <researchPrerequisite Inherit="False">Snek_SMG</researchPrerequisite>
                    </value>
            </li>
            <!-- OTs-23 -->
            <li Class="PatchOperationReplace">
                <xpath>Defs/ThingDef[defName="CE_Gun_OTS23a"]/recipeMaker/researchPrerequisite</xpath>
                    <value>
                        <researchPrerequisite Inherit="False">Snek_SMG</researchPrerequisite>
                    </value>
            </li>
            <!-- AK-80a -->
            <li Class="PatchOperationReplace">
                <xpath>Defs/ThingDef[defName="CE_Gun_AK80a"]/recipeMaker/researchPrerequisite</xpath>
                    <value>
                        <researchPrerequisite Inherit="False">Snek_SelectiveFire</researchPrerequisite>
                    </value>
            </li>
            <li Class="PatchOperationAdd">
                <xpath>Defs/ThingDef[defName="CE_Gun_AK80a"]/recipeMaker</xpath>
                    <value>
                        <researchPrerequisites>
                            <li>CE_Launchers</li>
                            <li>Snek_HighCaliber</li>
                        </researchPrerequisites>
                    </value>
            </li>
            <!-- AK-80b -->
            <li Class="PatchOperationAdd">
                <xpath>Defs/ThingDef[defName="CE_Gun_AK80b"]/recipeMaker</xpath>
                    <value>
                        <researchPrerequisites>
                            <li>CE_Launchers</li>
                            <li>Snek_Bakelite</li>
                            <li>Snek_HighCaliber</li>
                        </researchPrerequisites>
                    </value>
            </li>
            <!-- AKMP -->
            <li Class="PatchOperationReplace">
                <xpath>Defs/ThingDef[defName="CE_Gun_KripAKMS"]/recipeMaker/researchPrerequisite</xpath>
                    <value>
                        <researchPrerequisite Inherit="False">Snek_SelectiveFire</researchPrerequisite>
                    </value>
            </li>
            <!-- RPL-20 -->
            <li Class="PatchOperationAdd">
                <xpath>Defs/ThingDef[defName="CE_Gun_RPL-20a"]/recipeMaker</xpath>
                    <value>
                        <researchPrerequisites>
                            <li>Snek_AmmoBelts</li>
                            <li>Snek_Bakelite</li>
                        </researchPrerequisites>
                    </value>
            </li>
            <!-- ASh-12 -->
            <li Class="PatchOperationAdd">
                <xpath>Defs/ThingDef[defName="CE_Gun_Ash12a"]/recipeMaker</xpath>
                    <value>
                        <researchPrerequisites>
                            <li>Snek_HighCaliber</li>
                            <li>Snek_Bakelite</li>
                        </researchPrerequisites>
                    </value>
            </li>
            <!-- Groza -->
            <li Class="PatchOperationAdd">
                <xpath>Defs/ThingDef[defName="CE_Gun_OTS14a"]/recipeMaker</xpath>
                    <value>
                        <researchPrerequisites>
                            <li>Snek_SimpleScopes</li>
                            <li>Snek_Bakelite</li>
                        </researchPrerequisites>
                    </value>
            </li>
            <!-- Groza GL -->
            <li Class="PatchOperationAdd">
                <xpath>Defs/ThingDef[defName="CE_Gun_OTS14a"]/recipeMaker/researchPrerequisites</xpath>
                    <value>
                        <li>Snek_Bakelite</li>
                    </value>
            </li>
            <!-- SHRIMP (sr-1mp) -->
            <li Class="PatchOperationReplace">
                <xpath>Defs/ThingDef[defName="CE_Gun_SR1MP"]/recipeMaker/researchPrerequisite</xpath>
                    <value>
                        <researchPrerequisite Inherit="False">BlowbackOperation</researchPrerequisite>
                    </value>
            </li>

            <li Class="PatchOperationAdd">
                <xpath>Defs/ThingDef[defName="CE_Gun_SR1MP"]/recipeMaker</xpath>
                    <value>
                        <researchPrerequisites>
                            <li>Snek_Bakelite</li>
                            <li>CE_SimpleNV</li>
                        </researchPrerequisites>
                    </value>
            </li>
            <!-- Tulyak-11 -->
            <li Class="PatchOperationAdd">
                <xpath>Defs/ThingDef[defName="CE_Gun_Tulyak"]/recipeMaker</xpath>
                    <value>
                        <researchPrerequisites>
                            <li>Snek_HighCaliber</li>
                        </researchPrerequisites>
                    </value>
            </li>
            <!-- AK Drummer -->
            <li Class="PatchOperationReplace">
                <xpath>Defs/ThingDef[defName="CE_Gun_AK47a"]/recipeMaker/researchPrerequisite</xpath>
                    <value>
                        <researchPrerequisite Inherit="False">Snek_SelectiveFire</researchPrerequisite>
                    </value>
            </li>
            <!-- OP-SKS -->
            <li Class="PatchOperationAdd">
                <xpath>Defs/ThingDef[defName="CE_Gun_OPSKS"]/recipeMaker</xpath>
                    <value>
                        <researchPrerequisites>
                            <li>CE_SimpleNV</li>
                            <li>Snek_Bakelite</li>
                        </researchPrerequisites>
                    </value>
            </li>
            <!-- SR-2M -->
            <li Class="PatchOperationAdd">
                <xpath>Defs/ThingDef[defName="CE_Gun_SR2M"]/recipeMaker</xpath>
                    <value>
                        <researchPrerequisites>
                            <li>CE_SimpleNV</li>
                            <li>Snek_Bakelite</li>
                        </researchPrerequisites>
                    </value>
            </li>
        </operations>
        </match>
    </Operation>

</Patch>